cucounter
cucounter_backend
