Metadata-Version: 2.1
Name: kage-cucounter
Version: 1.0.1
Summary: A hashtable based counter implemented in CUDA for high throughput.
Author: Jørgen Henriksen
